pymagej/__init__.py
pymagej/roi.py
Pymagej-0.2.1.dist-info/AUTHORS.rst
Pymagej-0.2.1.dist-info/LICENSE.md
Pymagej-0.2.1.dist-info/METADATA
Pymagej-0.2.1.dist-info/WHEEL
Pymagej-0.2.1.dist-info/top_level.txt
Pymagej-0.2.1.dist-info/RECORD
